arcjetCV/__init__.py
arcjetCV/chessboard_pattern.png
arcjetCV/calibration/__init__.py
arcjetCV/calibration/calibrate_video.py
arcjetCV/calibration/calibration_controller.py
arcjetCV/calibration/calibration_main.py
arcjetCV/calibration/calibration_model.py
arcjetCV/calibration/calibration_view.py
arcjetCV/calibration/chessboard_pattern.png
arcjetCV/calibration/detetct_example.py
arcjetCV/calibration/rotated_pattern.png
arcjetCV/calibration/test.py
arcjetCV/gui/__init__.py
arcjetCV/gui/_arcjetCV_gui.py
arcjetCV/gui/arcjetCV_gui.py
arcjetCV/gui/custom_classes.py
arcjetCV/gui/main.py
arcjetCV/gui/main_window.py
arcjetCV/gui/logo/arcjetCV_logo.icns
arcjetCV/gui/logo/arcjetCV_logo.ico
arcjetCV/gui/logo/arcjetCV_logo_.png
arcjetCV/gui/logo/arcjetCV_logo_white.png
arcjetCV/segmentation/__init__.py
arcjetCV/segmentation/contour/__init__.py
arcjetCV/segmentation/contour/cnn.py
arcjetCV/segmentation/contour/contour.py
arcjetCV/segmentation/contour/conversion.py
arcjetCV/segmentation/contour/model_loader.py
arcjetCV/segmentation/time/__init__.py
arcjetCV/segmentation/time/time_segmentation.py
arcjetCV/utils/__init__.py
arcjetCV/utils/logger.py
arcjetCV/utils/output.py
arcjetCV/utils/processor.py
arcjetCV/utils/utils.py
arcjetCV/utils/video.py
arcjetcv-1.1.6.dist-info/licenses/LICENSE
tests/README.md
tests/__init__.py
tests/chessboard_pattern.png
tests/test_calibration_functions.py
tests/test_calibration_gui.py
tests/test_functions.py
tests/test_gui.py
tests/test_obj_models.py
tests/test_segmentation.py
arcjetcv-1.1.6.dist-info/METADATA
arcjetcv-1.1.6.dist-info/WHEEL
arcjetcv-1.1.6.dist-info/entry_points.txt
arcjetcv-1.1.6.dist-info/top_level.txt
arcjetcv-1.1.6.dist-info/RECORD
