Metadata-Version: 2.4
Name: arcjetcv
Version: 1.1.6
Summary: Package to process arcjet videos and segment the edge of the shock and of the sample
Home-page: https://github.com/magnus-haw/arcjetCV
Author: arcjetCV team
Project-URL: Bug Tracker, https://github.com/magnus-haw/arcjetCV/issues
Platform: Linux
Platform: Mac
Platform: Windows
Classifier: Development Status :: 5 - Production/Stable
Classifier: Operating System :: OS Independent
Classifier: Programming Language :: Python :: 3
Classifier: Topic :: Scientific/Engineering
Classifier: Topic :: Scientific/Engineering :: Physics
License-File: LICENSE
Requires-Dist: pyside6>=6.5.0
Requires-Dist: opencv-python
Requires-Dist: opencv-contrib-python
Requires-Dist: numpy
Requires-Dist: matplotlib
Requires-Dist: pandas
Requires-Dist: pyarrow
Requires-Dist: scikit-learn
Requires-Dist: segmentation-models-pytorch
Requires-Dist: torch
Requires-Dist: torchvision
Dynamic: author
Dynamic: classifier
Dynamic: description
Dynamic: description-content-type
Dynamic: home-page
Dynamic: license-file
Dynamic: platform
Dynamic: project-url
Dynamic: requires-dist
Dynamic: summary
